{
  "title": "Our Team",
  "description": "Meet the members of the OneLiteFeather team behind our projects. Last update: May 24, 2025",
  "ranks": [
    {
      "name": "Administration",
      "description": "Responsible for the management and financial direction of the platform.",
      "members": [
        {
          "name": "Seelenretterin",
          "slug": "seelenretterin",
          "bio": "Financial server owner and part of the administration. Also creates content for various social media to attract new players.",
          "profileImage": ""
        },
        {
          "name": "TheMeinerLP",
          "slug": "themeinerlp",
          "bio": "Financial server owner and part of the administration. Also active in development leadership.",
          "profileImage": ""
        },
        {
          "name": "theEvilReaper",
          "slug": "theevilreaper",
          "bio": "Member of the administration. Also active in development leadership.",
          "profileImage": ""
        }
      ]
    },
    {
      "name": "Development Leadership",
      "description": "Manages servers, supports new developers, and makes technology decisions.",
      "members": [
        {
          "name": "TheMeinerLP",
          "slug": "themeinerlp",
          "bio": "Manages servers, supports new developers, and helps with questions. Makes decisions about which technologies to implement based on expertise.",
          "profileImage": ""
        },
        {
          "name": "theEvilReaper",
          "slug": "theevilreaper",
          "bio": "Manages servers, supports new developers, and helps with questions. Makes decisions about which technologies to implement based on expertise.",
          "profileImage": ""
        }
      ]
    },
    {
      "name": "Builder",
      "description": "Creative minds who shape our worlds.",
      "members": [
        {
          "name": "PegasusFieber17",
          "slug": "pegasusfieber17",
          "bio": "Building leadership. Builds villages, redstone circuits, and other projects.",
          "profileImage": ""
        }
      ]
    },
    {
      "name": "Developer",
      "description": "Develop plugins, AI, RestApis, and other technical solutions.",
      "members": [
        {
          "name": "Joltra",
          "slug": "joltra",
          "bio": "Developer at OneLiteFeather. Works on plugins, AI, and RestApis.",
          "profileImage": ""
        },
        {
          "name": "Random (3s1)",
          "slug": "random-3s1",
          "bio": "Developer at OneLiteFeather. Works on plugins, AI, and RestApis.",
          "profileImage": ""
        },
        {
          "name": "theShadowsDust",
          "slug": "theshadowsdust",
          "bio": "Developer at OneLiteFeather. Works on plugins, AI, and RestApis.",
          "profileImage": ""
        }
      ]
    },
    {
      "name": "System Integrators",
      "description": "Take care of server infrastructure, security, and automation.",
      "members": [
        {
          "name": "Saynax",
          "slug": "saynax",
          "bio": "Server whisperer who ensures servers are protected. Also develops automation solutions (DevOps).",
          "profileImage": ""
        },
        {
          "name": "mcmdev",
          "slug": "mcmdev",
          "bio": "Server whisperer who ensures servers are protected. Also develops automation solutions (DevOps).",
          "profileImage": ""
        }
      ]
    },
    {
      "name": "Marketing",
      "description": "Creates content for social media and attracts new players.",
      "members": [
        {
          "name": "Seelenretterin",
          "slug": "seelenretterin",
          "bio": "Creates content for various social media to attract new players.",
          "profileImage": ""
        }
      ]
    },
    {
      "name": "Writer",
      "description": "Create concepts for game modes and translate them into features for plugins.",
      "members": [
        {
          "name": "weltspielt",
          "slug": "weltspielt",
          "bio": "Takes care of concepts for game modes and ensures that concepts are translated into features for plugins that developers implement in versions.",
          "profileImage": ""
        }
      ]
    },
    {
      "name": "Moderation",
      "description": "Supports players and ensures rules are followed.",
      "members": [
        {
          "name": "Morelia0815",
          "slug": "morelia0815",
          "bio": "Ensures that players are supported and rules are followed. Direct contact for issues related to the Minecraft server.",
          "profileImage": ""
        },
        {
          "name": "blndr2",
          "slug": "blndr2",
          "bio": "Ensures that players are supported and rules are followed. Direct contact for issues related to the Minecraft server.",
          "profileImage": ""
        }
      ]
    }
  ],
  "rankExplanations": [
    {
      "rank": "Administration",
      "description": "The administration consists of financial server owners and other members responsible for management and strategic direction."
    },
    {
      "rank": "Development Leadership",
      "description": "The development leadership manages servers, supports new developers, and makes decisions about which technologies to implement based on expertise."
    },
    {
      "rank": "Builder",
      "description": "Builders work on villages, redstone circuits, and other projects to shape the game world."
    },
    {
      "rank": "Developer",
      "description": "Developers work on plugins, AI, RestApis, and other technical solutions for the server."
    },
    {
      "rank": "System Integrators",
      "description": "System integrators take care of server infrastructure, security, and automation (DevOps)."
    },
    {
      "rank": "Marketing",
      "description": "The marketing team creates content for social media to attract new players."
    },
    {
      "rank": "Writer",
      "description": "Writers create concepts for game modes and translate them into features for plugins that are implemented by developers."
    },
    {
      "rank": "Moderation",
      "description": "Moderators support players, ensure rules are followed, and are direct contacts for issues related to the Minecraft server."
    }
  ]
}
